[
  {
    "id": 68459569,
    "node_id": "MDEwOlJlcG9zaXRvcnk2ODQ1OTU2OQ==",
    "name": "iroha-ios",
    "full_name": "hyperledger/iroha-ios",
    "private": false,
    "owner": {
      "login": "hyperledger",
      "id": 7657900,
      "node_id": "MDEyOk9yZ2FuaXphdGlvbjc2NTc5MDA=",
      "avatar_url": "https://avatars.githubusercontent.com/u/7657900?v=4",
      "gravatar_id": "",
      "url": "https://api.github.com/users/hyperledger",
      "html_url": "https://github.com/hyperledger",
      "followers_url": "https://api.github.com/users/hyperledger/followers",
      "following_url": "https://api.github.com/users/hyperledger/following{/other_user}",
      "gists_url": "https://api.github.com/users/hyperledger/gists{/gist_id}",
      "starred_url": "https://api.github.com/users/hyperledger/starred{/owner}{/repo}",
      "subscriptions_url": "https://api.github.com/users/hyperledger/subscriptions",
      "organizations_url": "https://api.github.com/users/hyperledger/orgs",
      "repos_url": "https://api.github.com/users/hyperledger/repos",
      "events_url": "https://api.github.com/users/hyperledger/events{/privacy}",
      "received_events_url": "https://api.github.com/users/hyperledger/received_events",
      "type": "Organization",
      "site_admin": false
    },
    "html_url": "https://github.com/hyperledger/iroha-ios",
    "description": "iOS Swift library for Iroha, a simple distributed ledger",
    "fork": false,
    "url": "https://api.github.com/repos/hyperledger/iroha-ios",
    "forks_url": "https://api.github.com/repos/hyperledger/iroha-ios/forks",
    "keys_url": "https://api.github.com/repos/hyperledger/iroha-ios/keys{/key_id}",
    "collaborators_url": "https://api.github.com/repos/hyperledger/iroha-ios/collaborators{/collaborator}",
    "teams_url": "https://api.github.com/repos/hyperledger/iroha-ios/teams",
    "hooks_url": "https://api.github.com/repos/hyperledger/iroha-ios/hooks",
    "issue_events_url": "https://api.github.com/repos/hyperledger/iroha-ios/issues/events{/number}",
    "events_url": "https://api.github.com/repos/hyperledger/iroha-ios/events",
    "assignees_url": "https://api.github.com/repos/hyperledger/iroha-ios/assignees{/user}",
    "branches_url": "https://api.github.com/repos/hyperledger/iroha-ios/branches{/branch}",
    "tags_url": "https://api.github.com/repos/hyperledger/iroha-ios/tags",
    "blobs_url": "https://api.github.com/repos/hyperledger/iroha-ios/git/blobs{/sha}",
    "git_tags_url": "https://api.github.com/repos/hyperledger/iroha-ios/git/tags{/sha}",
    "git_refs_url": "https://api.github.com/repos/hyperledger/iroha-ios/git/refs{/sha}",
    "trees_url": "https://api.github.com/repos/hyperledger/iroha-ios/git/trees{/sha}",
    "statuses_url": "https://api.github.com/repos/hyperledger/iroha-ios/statuses/{sha}",
    "languages_url": "https://api.github.com/repos/hyperledger/iroha-ios/languages",
    "stargazers_url": "https://api.github.com/repos/hyperledger/iroha-ios/stargazers",
    "contributors_url": "https://api.github.com/repos/hyperledger/iroha-ios/contributors",
    "subscribers_url": "https://api.github.com/repos/hyperledger/iroha-ios/subscribers",
    "subscription_url": "https://api.github.com/repos/hyperledger/iroha-ios/subscription",
    "commits_url": "https://api.github.com/repos/hyperledger/iroha-ios/commits{/sha}",
    "git_commits_url": "https://api.github.com/repos/hyperledger/iroha-ios/git/commits{/sha}",
    "comments_url": "https://api.github.com/repos/hyperledger/iroha-ios/comments{/number}",
    "issue_comment_url": "https://api.github.com/repos/hyperledger/iroha-ios/issues/comments{/number}",
    "contents_url": "https://api.github.com/repos/hyperledger/iroha-ios/contents/{+path}",
    "compare_url": "https://api.github.com/repos/hyperledger/iroha-ios/compare/{base}...{head}",
    "merges_url": "https://api.github.com/repos/hyperledger/iroha-ios/merges",
    "archive_url": "https://api.github.com/repos/hyperledger/iroha-ios/{archive_format}{/ref}",
    "downloads_url": "https://api.github.com/repos/hyperledger/iroha-ios/downloads",
    "issues_url": "https://api.github.com/repos/hyperledger/iroha-ios/issues{/number}",
    "pulls_url": "https://api.github.com/repos/hyperledger/iroha-ios/pulls{/number}",
    "milestones_url": "https://api.github.com/repos/hyperledger/iroha-ios/milestones{/number}",
    "notifications_url": "https://api.github.com/repos/hyperledger/iroha-ios/notifications{?since,all,participating}",
    "labels_url": "https://api.github.com/repos/hyperledger/iroha-ios/labels{/name}",
    "releases_url": "https://api.github.com/repos/hyperledger/iroha-ios/releases{/id}",
    "deployments_url": "https://api.github.com/repos/hyperledger/iroha-ios/deployments",
    "created_at": "2016-09-17T15:12:44Z",
    "updated_at": "2021-06-03T18:40:59Z",
    "pushed_at": "2021-06-03T18:40:56Z",
    "git_url": "git://github.com/hyperledger/iroha-ios.git",
    "ssh_url": "git@github.com:hyperledger/iroha-ios.git",
    "clone_url": "https://github.com/hyperledger/iroha-ios.git",
    "svn_url": "https://github.com/hyperledger/iroha-ios",
    "homepage": "https://wiki.hyperledger.org/display/iroha",
    "size": 117990,
    "stargazers_count": 85,
    "watchers_count": 85,
    "language": "Objective-C",
    "has_issues": true,
    "has_projects": true,
    "has_downloads": true,
    "has_wiki": true,
    "has_pages": false,
    "forks_count": 54,
    "mirror_url": null,
    "archived": false,
    "disabled": false,
    "open_issues_count": 2,
    "license": {
      "key": "other",
      "name": "Other",
      "spdx_id": "NOASSERTION",
      "url": null,
      "node_id": "MDc6TGljZW5zZTA="
    },
    "forks": 54,
    "open_issues": 2,
    "watchers": 85,
    "default_branch": "main",
    "permissions": {
      "pull": true,
      "triage": false,
      "push": false,
      "maintain": false,
      "admin": false
    }
  },
  {
    "id": 68600924,
    "node_id": "MDEwOlJlcG9zaXRvcnk2ODYwMDkyNA==",
    "name": "iroha-javascript",
    "full_name": "hyperledger/iroha-javascript",
    "private": false,
    "owner": {
      "login": "hyperledger",
      "id": 7657900,
      "node_id": "MDEyOk9yZ2FuaXphdGlvbjc2NTc5MDA=",
      "avatar_url": "https://avatars.githubusercontent.com/u/7657900?v=4",
      "gravatar_id": "",
      "url": "https://api.github.com/users/hyperledger",
      "html_url": "https://github.com/hyperledger",
      "followers_url": "https://api.github.com/users/hyperledger/followers",
      "following_url": "https://api.github.com/users/hyperledger/following{/other_user}",
      "gists_url": "https://api.github.com/users/hyperledger/gists{/gist_id}",
      "starred_url": "https://api.github.com/users/hyperledger/starred{/owner}{/repo}",
      "subscriptions_url": "https://api.github.com/users/hyperledger/subscriptions",
      "organizations_url": "https://api.github.com/users/hyperledger/orgs",
      "repos_url": "https://api.github.com/users/hyperledger/repos",
      "events_url": "https://api.github.com/users/hyperledger/events{/privacy}",
      "received_events_url": "https://api.github.com/users/hyperledger/received_events",
      "type": "Organization",
      "site_admin": false
    },
    "html_url": "https://github.com/hyperledger/iroha-javascript",
    "description": "JavaScript library for Iroha, a Distributed Ledger Technology (blockchain) platform.",
    "fork": false,
    "url": "https://api.github.com/repos/hyperledger/iroha-javascript",
    "forks_url": "https://api.github.com/repos/hyperledger/iroha-javascript/forks",
    "keys_url": "https://api.github.com/repos/hyperledger/iroha-javascript/keys{/key_id}",
    "collaborators_url": "https://api.github.com/repos/hyperledger/iroha-javascript/collaborators{/collaborator}",
    "teams_url": "https://api.github.com/repos/hyperledger/iroha-javascript/teams",
    "hooks_url": "https://api.github.com/repos/hyperledger/iroha-javascript/hooks",
    "issue_events_url": "https://api.github.com/repos/hyperledger/iroha-javascript/issues/events{/number}",
    "events_url": "https://api.github.com/repos/hyperledger/iroha-javascript/events",
    "assignees_url": "https://api.github.com/repos/hyperledger/iroha-javascript/assignees{/user}",
    "branches_url": "https://api.github.com/repos/hyperledger/iroha-javascript/branches{/branch}",
    "tags_url": "https://api.github.com/repos/hyperledger/iroha-javascript/tags",
    "blobs_url": "https://api.github.com/repos/hyperledger/iroha-javascript/git/blobs{/sha}",
    "git_tags_url": "https://api.github.com/repos/hyperledger/iroha-javascript/git/tags{/sha}",
    "git_refs_url": "https://api.github.com/repos/hyperledger/iroha-javascript/git/refs{/sha}",
    "trees_url": "https://api.github.com/repos/hyperledger/iroha-javascript/git/trees{/sha}",
    "statuses_url": "https://api.github.com/repos/hyperledger/iroha-javascript/statuses/{sha}",
    "languages_url": "https://api.github.com/repos/hyperledger/iroha-javascript/languages",
    "stargazers_url": "https://api.github.com/repos/hyperledger/iroha-javascript/stargazers",
    "contributors_url": "https://api.github.com/repos/hyperledger/iroha-javascript/contributors",
    "subscribers_url": "https://api.github.com/repos/hyperledger/iroha-javascript/subscribers",
    "subscription_url": "https://api.github.com/repos/hyperledger/iroha-javascript/subscription",
    "commits_url": "https://api.github.com/repos/hyperledger/iroha-javascript/commits{/sha}",
    "git_commits_url": "https://api.github.com/repos/hyperledger/iroha-javascript/git/commits{/sha}",
    "comments_url": "https://api.github.com/repos/hyperledger/iroha-javascript/comments{/number}",
    "issue_comment_url": "https://api.github.com/repos/hyperledger/iroha-javascript/issues/comments{/number}",
    "contents_url": "https://api.github.com/repos/hyperledger/iroha-javascript/contents/{+path}",
    "compare_url": "https://api.github.com/repos/hyperledger/iroha-javascript/compare/{base}...{head}",
    "merges_url": "https://api.github.com/repos/hyperledger/iroha-javascript/merges",
    "archive_url": "https://api.github.com/repos/hyperledger/iroha-javascript/{archive_format}{/ref}",
    "downloads_url": "https://api.github.com/repos/hyperledger/iroha-javascript/downloads",
    "issues_url": "https://api.github.com/repos/hyperledger/iroha-javascript/issues{/number}",
    "pulls_url": "https://api.github.com/repos/hyperledger/iroha-javascript/pulls{/number}",
    "milestones_url": "https://api.github.com/repos/hyperledger/iroha-javascript/milestones{/number}",
    "notifications_url": "https://api.github.com/repos/hyperledger/iroha-javascript/notifications{?since,all,participating}",
    "labels_url": "https://api.github.com/repos/hyperledger/iroha-javascript/labels{/name}",
    "releases_url": "https://api.github.com/repos/hyperledger/iroha-javascript/releases{/id}",
    "deployments_url": "https://api.github.com/repos/hyperledger/iroha-javascript/deployments",
    "created_at": "2016-09-19T11:51:46Z",
    "updated_at": "2021-06-09T07:40:56Z",
    "pushed_at": "2021-06-09T07:41:03Z",
    "git_url": "git://github.com/hyperledger/iroha-javascript.git",
    "ssh_url": "git@github.com:hyperledger/iroha-javascript.git",
    "clone_url": "https://github.com/hyperledger/iroha-javascript.git",
    "svn_url": "https://github.com/hyperledger/iroha-javascript",
    "homepage": "https://wiki.hyperledger.org/display/iroha",
    "size": 1144,
    "stargazers_count": 80,
    "watchers_count": 80,
    "language": "JavaScript",
    "has_issues": true,
    "has_projects": true,
    "has_downloads": true,
    "has_wiki": true,
    "has_pages": false,
    "forks_count": 45,
    "mirror_url": null,
    "archived": false,
    "disabled": false,
    "open_issues_count": 1,
    "license": {
      "key": "apache-2.0",
      "name": "Apache License 2.0",
      "spdx_id": "Apache-2.0",
      "url": "https://api.github.com/licenses/apache-2.0",
      "node_id": "MDc6TGljZW5zZTI="
    },
    "forks": 45,
    "open_issues": 1,
    "watchers": 80,
    "default_branch": "master",
    "permissions": {
      "pull": true,
      "triage": false,
      "push": false,
      "maintain": false,
      "admin": false
    }
  },
  {
    "id": 83542442,
    "node_id": "MDEwOlJlcG9zaXRvcnk4MzU0MjQ0Mg==",
    "name": "iroha-python",
    "full_name": "hyperledger/iroha-python",
    "private": false,
    "owner": {
      "login": "hyperledger",
      "id": 7657900,
      "node_id": "MDEyOk9yZ2FuaXphdGlvbjc2NTc5MDA=",
      "avatar_url": "https://avatars.githubusercontent.com/u/7657900?v=4",
      "gravatar_id": "",
      "url": "https://api.github.com/users/hyperledger",
      "html_url": "https://github.com/hyperledger",
      "followers_url": "https://api.github.com/users/hyperledger/followers",
      "following_url": "https://api.github.com/users/hyperledger/following{/other_user}",
      "gists_url": "https://api.github.com/users/hyperledger/gists{/gist_id}",
      "starred_url": "https://api.github.com/users/hyperledger/starred{/owner}{/repo}",
      "subscriptions_url": "https://api.github.com/users/hyperledger/subscriptions",
      "organizations_url": "https://api.github.com/users/hyperledger/orgs",
      "repos_url": "https://api.github.com/users/hyperledger/repos",
      "events_url": "https://api.github.com/users/hyperledger/events{/privacy}",
      "received_events_url": "https://api.github.com/users/hyperledger/received_events",
      "type": "Organization",
      "site_admin": false
    },
    "html_url": "https://github.com/hyperledger/iroha-python",
    "description": "Python library for Hyperledger Iroha, a simple distributed ledger.",
    "fork": false,
    "url": "https://api.github.com/repos/hyperledger/iroha-python",
    "forks_url": "https://api.github.com/repos/hyperledger/iroha-python/forks",
    "keys_url": "https://api.github.com/repos/hyperledger/iroha-python/keys{/key_id}",
    "collaborators_url": "https://api.github.com/repos/hyperledger/iroha-python/collaborators{/collaborator}",
    "teams_url": "https://api.github.com/repos/hyperledger/iroha-python/teams",
    "hooks_url": "https://api.github.com/repos/hyperledger/iroha-python/hooks",
    "issue_events_url": "https://api.github.com/repos/hyperledger/iroha-python/issues/events{/number}",
    "events_url": "https://api.github.com/repos/hyperledger/iroha-python/events",
    "assignees_url": "https://api.github.com/repos/hyperledger/iroha-python/assignees{/user}",
    "branches_url": "https://api.github.com/repos/hyperledger/iroha-python/branches{/branch}",
    "tags_url": "https://api.github.com/repos/hyperledger/iroha-python/tags",
    "blobs_url": "https://api.github.com/repos/hyperledger/iroha-python/git/blobs{/sha}",
    "git_tags_url": "https://api.github.com/repos/hyperledger/iroha-python/git/tags{/sha}",
    "git_refs_url": "https://api.github.com/repos/hyperledger/iroha-python/git/refs{/sha}",
    "trees_url": "https://api.github.com/repos/hyperledger/iroha-python/git/trees{/sha}",
    "statuses_url": "https://api.github.com/repos/hyperledger/iroha-python/statuses/{sha}",
    "languages_url": "https://api.github.com/repos/hyperledger/iroha-python/languages",
    "stargazers_url": "https://api.github.com/repos/hyperledger/iroha-python/stargazers",
    "contributors_url": "https://api.github.com/repos/hyperledger/iroha-python/contributors",
    "subscribers_url": "https://api.github.com/repos/hyperledger/iroha-python/subscribers",
    "subscription_url": "https://api.github.com/repos/hyperledger/iroha-python/subscription",
    "commits_url": "https://api.github.com/repos/hyperledger/iroha-python/commits{/sha}",
    "git_commits_url": "https://api.github.com/repos/hyperledger/iroha-python/git/commits{/sha}",
    "comments_url": "https://api.github.com/repos/hyperledger/iroha-python/comments{/number}",
    "issue_comment_url": "https://api.github.com/repos/hyperledger/iroha-python/issues/comments{/number}",
    "contents_url": "https://api.github.com/repos/hyperledger/iroha-python/contents/{+path}",
    "compare_url": "https://api.github.com/repos/hyperledger/iroha-python/compare/{base}...{head}",
    "merges_url": "https://api.github.com/repos/hyperledger/iroha-python/merges",
    "archive_url": "https://api.github.com/repos/hyperledger/iroha-python/{archive_format}{/ref}",
    "downloads_url": "https://api.github.com/repos/hyperledger/iroha-python/downloads",
    "issues_url": "https://api.github.com/repos/hyperledger/iroha-python/issues{/number}",
    "pulls_url": "https://api.github.com/repos/hyperledger/iroha-python/pulls{/number}",
    "milestones_url": "https://api.github.com/repos/hyperledger/iroha-python/milestones{/number}",
    "notifications_url": "https://api.github.com/repos/hyperledger/iroha-python/notifications{?since,all,participating}",
    "labels_url": "https://api.github.com/repos/hyperledger/iroha-python/labels{/name}",
    "releases_url": "https://api.github.com/repos/hyperledger/iroha-python/releases{/id}",
    "deployments_url": "https://api.github.com/repos/hyperledger/iroha-python/deployments",
    "created_at": "2017-03-01T10:29:10Z",
    "updated_at": "2021-05-02T07:23:09Z",
    "pushed_at": "2021-05-21T09:21:52Z",
    "git_url": "git://github.com/hyperledger/iroha-python.git",
    "ssh_url": "git@github.com:hyperledger/iroha-python.git",
    "clone_url": "https://github.com/hyperledger/iroha-python.git",
    "svn_url": "https://github.com/hyperledger/iroha-python",
    "homepage": "https://wiki.hyperledger.org/display/iroha",
    "size": 730,
    "stargazers_count": 85,
    "watchers_count": 85,
    "language": "Python",
    "has_issues": true,
    "has_projects": true,
    "has_downloads": true,
    "has_wiki": true,
    "has_pages": false,
    "forks_count": 59,
    "mirror_url": null,
    "archived": false,
    "disabled": false,
    "open_issues_count": 7,
    "license": {
      "key": "apache-2.0",
      "name": "Apache License 2.0",
      "spdx_id": "Apache-2.0",
      "url": "https://api.github.com/licenses/apache-2.0",
      "node_id": "MDc6TGljZW5zZTI="
    },
    "forks": 59,
    "open_issues": 7,
    "watchers": 85,
    "default_branch": "master",
    "permissions": {
      "pull": true,
      "triage": false,
      "push": false,
      "maintain": false,
      "admin": false
    }
  },
  {
    "id": 166456657,
    "node_id": "MDEwOlJlcG9zaXRvcnkxNjY0NTY2NTc=",
    "name": "iroha-java",
    "full_name": "hyperledger/iroha-java",
    "private": false,
    "owner": {
      "login": "hyperledger",
      "id": 7657900,
      "node_id": "MDEyOk9yZ2FuaXphdGlvbjc2NTc5MDA=",
      "avatar_url": "https://avatars.githubusercontent.com/u/7657900?v=4",
      "gravatar_id": "",
      "url": "https://api.github.com/users/hyperledger",
      "html_url": "https://github.com/hyperledger",
      "followers_url": "https://api.github.com/users/hyperledger/followers",
      "following_url": "https://api.github.com/users/hyperledger/following{/other_user}",
      "gists_url": "https://api.github.com/users/hyperledger/gists{/gist_id}",
      "starred_url": "https://api.github.com/users/hyperledger/starred{/owner}{/repo}",
      "subscriptions_url": "https://api.github.com/users/hyperledger/subscriptions",
      "organizations_url": "https://api.github.com/users/hyperledger/orgs",
      "repos_url": "https://api.github.com/users/hyperledger/repos",
      "events_url": "https://api.github.com/users/hyperledger/events{/privacy}",
      "received_events_url": "https://api.github.com/users/hyperledger/received_events",
      "type": "Organization",
      "site_admin": false
    },
    "html_url": "https://github.com/hyperledger/iroha-java",
    "description": null,
    "fork": false,
    "url": "https://api.github.com/repos/hyperledger/iroha-java",
    "forks_url": "https://api.github.com/repos/hyperledger/iroha-java/forks",
    "keys_url": "https://api.github.com/repos/hyperledger/iroha-java/keys{/key_id}",
    "collaborators_url": "https://api.github.com/repos/hyperledger/iroha-java/collaborators{/collaborator}",
    "teams_url": "https://api.github.com/repos/hyperledger/iroha-java/teams",
    "hooks_url": "https://api.github.com/repos/hyperledger/iroha-java/hooks",
    "issue_events_url": "https://api.github.com/repos/hyperledger/iroha-java/issues/events{/number}",
    "events_url": "https://api.github.com/repos/hyperledger/iroha-java/events",
    "assignees_url": "https://api.github.com/repos/hyperledger/iroha-java/assignees{/user}",
    "branches_url": "https://api.github.com/repos/hyperledger/iroha-java/branches{/branch}",
    "tags_url": "https://api.github.com/repos/hyperledger/iroha-java/tags",
    "blobs_url": "https://api.github.com/repos/hyperledger/iroha-java/git/blobs{/sha}",
    "git_tags_url": "https://api.github.com/repos/hyperledger/iroha-java/git/tags{/sha}",
    "git_refs_url": "https://api.github.com/repos/hyperledger/iroha-java/git/refs{/sha}",
    "trees_url": "https://api.github.com/repos/hyperledger/iroha-java/git/trees{/sha}",
    "statuses_url": "https://api.github.com/repos/hyperledger/iroha-java/statuses/{sha}",
    "languages_url": "https://api.github.com/repos/hyperledger/iroha-java/languages",
    "stargazers_url": "https://api.github.com/repos/hyperledger/iroha-java/stargazers",
    "contributors_url": "https://api.github.com/repos/hyperledger/iroha-java/contributors",
    "subscribers_url": "https://api.github.com/repos/hyperledger/iroha-java/subscribers",
    "subscription_url": "https://api.github.com/repos/hyperledger/iroha-java/subscription",
    "commits_url": "https://api.github.com/repos/hyperledger/iroha-java/commits{/sha}",
    "git_commits_url": "https://api.github.com/repos/hyperledger/iroha-java/git/commits{/sha}",
    "comments_url": "https://api.github.com/repos/hyperledger/iroha-java/comments{/number}",
    "issue_comment_url": "https://api.github.com/repos/hyperledger/iroha-java/issues/comments{/number}",
    "contents_url": "https://api.github.com/repos/hyperledger/iroha-java/contents/{+path}",
    "compare_url": "https://api.github.com/repos/hyperledger/iroha-java/compare/{base}...{head}",
    "merges_url": "https://api.github.com/repos/hyperledger/iroha-java/merges",
    "archive_url": "https://api.github.com/repos/hyperledger/iroha-java/{archive_format}{/ref}",
    "downloads_url": "https://api.github.com/repos/hyperledger/iroha-java/downloads",
    "issues_url": "https://api.github.com/repos/hyperledger/iroha-java/issues{/number}",
    "pulls_url": "https://api.github.com/repos/hyperledger/iroha-java/pulls{/number}",
    "milestones_url": "https://api.github.com/repos/hyperledger/iroha-java/milestones{/number}",
    "notifications_url": "https://api.github.com/repos/hyperledger/iroha-java/notifications{?since,all,participating}",
    "labels_url": "https://api.github.com/repos/hyperledger/iroha-java/labels{/name}",
    "releases_url": "https://api.github.com/repos/hyperledger/iroha-java/releases{/id}",
    "deployments_url": "https://api.github.com/repos/hyperledger/iroha-java/deployments",
    "created_at": "2019-01-18T18:46:04Z",
    "updated_at": "2021-06-03T18:41:29Z",
    "pushed_at": "2021-06-07T07:36:07Z",
    "git_url": "git://github.com/hyperledger/iroha-java.git",
    "ssh_url": "git@github.com:hyperledger/iroha-java.git",
    "clone_url": "https://github.com/hyperledger/iroha-java.git",
    "svn_url": "https://github.com/hyperledger/iroha-java",
    "homepage": "https://wiki.hyperledger.org/display/iroha",
    "size": 384,
    "stargazers_count": 23,
    "watchers_count": 23,
    "language": "Java",
    "has_issues": true,
    "has_projects": false,
    "has_downloads": true,
    "has_wiki": false,
    "has_pages": false,
    "forks_count": 18,
    "mirror_url": null,
    "archived": false,
    "disabled": false,
    "open_issues_count": 1,
    "license": {
      "key": "apache-2.0",
      "name": "Apache License 2.0",
      "spdx_id": "Apache-2.0",
      "url": "https://api.github.com/licenses/apache-2.0",
      "node_id": "MDc6TGljZW5zZTI="
    },
    "forks": 18,
    "open_issues": 1,
    "watchers": 23,
    "default_branch": "main",
    "permissions": {
      "pull": true,
      "triage": false,
      "push": false,
      "maintain": false,
      "admin": false
    }
  },
  {
    "id": 181739240,
    "node_id": "MDEwOlJlcG9zaXRvcnkxODE3MzkyNDA=",
    "name": "iroha",
    "full_name": "hyperledger/iroha",
    "private": false,
    "owner": {
      "login": "hyperledger",
      "id": 7657900,
      "node_id": "MDEyOk9yZ2FuaXphdGlvbjc2NTc5MDA=",
      "avatar_url": "https://avatars.githubusercontent.com/u/7657900?v=4",
      "gravatar_id": "",
      "url": "https://api.github.com/users/hyperledger",
      "html_url": "https://github.com/hyperledger",
      "followers_url": "https://api.github.com/users/hyperledger/followers",
      "following_url": "https://api.github.com/users/hyperledger/following{/other_user}",
      "gists_url": "https://api.github.com/users/hyperledger/gists{/gist_id}",
      "starred_url": "https://api.github.com/users/hyperledger/starred{/owner}{/repo}",
      "subscriptions_url": "https://api.github.com/users/hyperledger/subscriptions",
      "organizations_url": "https://api.github.com/users/hyperledger/orgs",
      "repos_url": "https://api.github.com/users/hyperledger/repos",
      "events_url": "https://api.github.com/users/hyperledger/events{/privacy}",
      "received_events_url": "https://api.github.com/users/hyperledger/received_events",
      "type": "Organization",
      "site_admin": false
    },
    "html_url": "https://github.com/hyperledger/iroha",
    "description": "Iroha - A simple, enterprise-grade decentralized ledger",
    "fork": false,
    "url": "https://api.github.com/repos/hyperledger/iroha",
    "forks_url": "https://api.github.com/repos/hyperledger/iroha/forks",
    "keys_url": "https://api.github.com/repos/hyperledger/iroha/keys{/key_id}",
    "collaborators_url": "https://api.github.com/repos/hyperledger/iroha/collaborators{/collaborator}",
    "teams_url": "https://api.github.com/repos/hyperledger/iroha/teams",
    "hooks_url": "https://api.github.com/repos/hyperledger/iroha/hooks",
    "issue_events_url": "https://api.github.com/repos/hyperledger/iroha/issues/events{/number}",
    "events_url": "https://api.github.com/repos/hyperledger/iroha/events",
    "assignees_url": "https://api.github.com/repos/hyperledger/iroha/assignees{/user}",
    "branches_url": "https://api.github.com/repos/hyperledger/iroha/branches{/branch}",
    "tags_url": "https://api.github.com/repos/hyperledger/iroha/tags",
    "blobs_url": "https://api.github.com/repos/hyperledger/iroha/git/blobs{/sha}",
    "git_tags_url": "https://api.github.com/repos/hyperledger/iroha/git/tags{/sha}",
    "git_refs_url": "https://api.github.com/repos/hyperledger/iroha/git/refs{/sha}",
    "trees_url": "https://api.github.com/repos/hyperledger/iroha/git/trees{/sha}",
    "statuses_url": "https://api.github.com/repos/hyperledger/iroha/statuses/{sha}",
    "languages_url": "https://api.github.com/repos/hyperledger/iroha/languages",
    "stargazers_url": "https://api.github.com/repos/hyperledger/iroha/stargazers",
    "contributors_url": "https://api.github.com/repos/hyperledger/iroha/contributors",
    "subscribers_url": "https://api.github.com/repos/hyperledger/iroha/subscribers",
    "subscription_url": "https://api.github.com/repos/hyperledger/iroha/subscription",
    "commits_url": "https://api.github.com/repos/hyperledger/iroha/commits{/sha}",
    "git_commits_url": "https://api.github.com/repos/hyperledger/iroha/git/commits{/sha}",
    "comments_url": "https://api.github.com/repos/hyperledger/iroha/comments{/number}",
    "issue_comment_url": "https://api.github.com/repos/hyperledger/iroha/issues/comments{/number}",
    "contents_url": "https://api.github.com/repos/hyperledger/iroha/contents/{+path}",
    "compare_url": "https://api.github.com/repos/hyperledger/iroha/compare/{base}...{head}",
    "merges_url": "https://api.github.com/repos/hyperledger/iroha/merges",
    "archive_url": "https://api.github.com/repos/hyperledger/iroha/{archive_format}{/ref}",
    "downloads_url": "https://api.github.com/repos/hyperledger/iroha/downloads",
    "issues_url": "https://api.github.com/repos/hyperledger/iroha/issues{/number}",
    "pulls_url": "https://api.github.com/repos/hyperledger/iroha/pulls{/number}",
    "milestones_url": "https://api.github.com/repos/hyperledger/iroha/milestones{/number}",
    "notifications_url": "https://api.github.com/repos/hyperledger/iroha/notifications{?since,all,participating}",
    "labels_url": "https://api.github.com/repos/hyperledger/iroha/labels{/name}",
    "releases_url": "https://api.github.com/repos/hyperledger/iroha/releases{/id}",
    "deployments_url": "https://api.github.com/repos/hyperledger/iroha/deployments",
    "created_at": "2019-04-16T17:50:11Z",
    "updated_at": "2021-06-14T15:41:47Z",
    "pushed_at": "2021-06-24T13:38:55Z",
    "git_url": "git://github.com/hyperledger/iroha.git",
    "ssh_url": "git@github.com:hyperledger/iroha.git",
    "clone_url": "https://github.com/hyperledger/iroha.git",
    "svn_url": "https://github.com/hyperledger/iroha",
    "homepage": "https://wiki.hyperledger.org/display/iroha",
    "size": 11318,
    "stargazers_count": 242,
    "watchers_count": 242,
    "language": "C++",
    "has_issues": true,
    "has_projects": true,
    "has_downloads": true,
    "has_wiki": false,
    "has_pages": false,
    "forks_count": 150,
    "mirror_url": null,
    "archived": false,
    "disabled": false,
    "open_issues_count": 76,
    "license": {
      "key": "apache-2.0",
      "name": "Apache License 2.0",
      "spdx_id": "Apache-2.0",
      "url": "https://api.github.com/licenses/apache-2.0",
      "node_id": "MDc6TGljZW5zZTI="
    },
    "forks": 150,
    "open_issues": 76,
    "watchers": 242,
    "default_branch": "main",
    "permissions": {
      "pull": false,
      "triage": false,
      "push": false,
      "maintain": true,
      "admin": false
    }
  },
  {
    "id": 217092085,
    "node_id": "MDEwOlJlcG9zaXRvcnkyMTcwOTIwODU=",
    "name": "iroha-tui-client",
    "full_name": "hyperledger/iroha-tui-client",
    "private": false,
    "owner": {
      "login": "hyperledger",
      "id": 7657900,
      "node_id": "MDEyOk9yZ2FuaXphdGlvbjc2NTc5MDA=",
      "avatar_url": "https://avatars.githubusercontent.com/u/7657900?v=4",
      "gravatar_id": "",
      "url": "https://api.github.com/users/hyperledger",
      "html_url": "https://github.com/hyperledger",
      "followers_url": "https://api.github.com/users/hyperledger/followers",
      "following_url": "https://api.github.com/users/hyperledger/following{/other_user}",
      "gists_url": "https://api.github.com/users/hyperledger/gists{/gist_id}",
      "starred_url": "https://api.github.com/users/hyperledger/starred{/owner}{/repo}",
      "subscriptions_url": "https://api.github.com/users/hyperledger/subscriptions",
      "organizations_url": "https://api.github.com/users/hyperledger/orgs",
      "repos_url": "https://api.github.com/users/hyperledger/repos",
      "events_url": "https://api.github.com/users/hyperledger/events{/privacy}",
      "received_events_url": "https://api.github.com/users/hyperledger/received_events",
      "type": "Organization",
      "site_admin": false
    },
    "html_url": "https://github.com/hyperledger/iroha-tui-client",
    "description": "iroha-tui-client",
    "fork": false,
    "url": "https://api.github.com/repos/hyperledger/iroha-tui-client",
    "forks_url": "https://api.github.com/repos/hyperledger/iroha-tui-client/forks",
    "keys_url": "https://api.github.com/repos/hyperledger/iroha-tui-client/keys{/key_id}",
    "collaborators_url": "https://api.github.com/repos/hyperledger/iroha-tui-client/collaborators{/collaborator}",
    "teams_url": "https://api.github.com/repos/hyperledger/iroha-tui-client/teams",
    "hooks_url": "https://api.github.com/repos/hyperledger/iroha-tui-client/hooks",
    "issue_events_url": "https://api.github.com/repos/hyperledger/iroha-tui-client/issues/events{/number}",
    "events_url": "https://api.github.com/repos/hyperledger/iroha-tui-client/events",
    "assignees_url": "https://api.github.com/repos/hyperledger/iroha-tui-client/assignees{/user}",
    "branches_url": "https://api.github.com/repos/hyperledger/iroha-tui-client/branches{/branch}",
    "tags_url": "https://api.github.com/repos/hyperledger/iroha-tui-client/tags",
    "blobs_url": "https://api.github.com/repos/hyperledger/iroha-tui-client/git/blobs{/sha}",
    "git_tags_url": "https://api.github.com/repos/hyperledger/iroha-tui-client/git/tags{/sha}",
    "git_refs_url": "https://api.github.com/repos/hyperledger/iroha-tui-client/git/refs{/sha}",
    "trees_url": "https://api.github.com/repos/hyperledger/iroha-tui-client/git/trees{/sha}",
    "statuses_url": "https://api.github.com/repos/hyperledger/iroha-tui-client/statuses/{sha}",
    "languages_url": "https://api.github.com/repos/hyperledger/iroha-tui-client/languages",
    "stargazers_url": "https://api.github.com/repos/hyperledger/iroha-tui-client/stargazers",
    "contributors_url": "https://api.github.com/repos/hyperledger/iroha-tui-client/contributors",
    "subscribers_url": "https://api.github.com/repos/hyperledger/iroha-tui-client/subscribers",
    "subscription_url": "https://api.github.com/repos/hyperledger/iroha-tui-client/subscription",
    "commits_url": "https://api.github.com/repos/hyperledger/iroha-tui-client/commits{/sha}",
    "git_commits_url": "https://api.github.com/repos/hyperledger/iroha-tui-client/git/commits{/sha}",
    "comments_url": "https://api.github.com/repos/hyperledger/iroha-tui-client/comments{/number}",
    "issue_comment_url": "https://api.github.com/repos/hyperledger/iroha-tui-client/issues/comments{/number}",
    "contents_url": "https://api.github.com/repos/hyperledger/iroha-tui-client/contents/{+path}",
    "compare_url": "https://api.github.com/repos/hyperledger/iroha-tui-client/compare/{base}...{head}",
    "merges_url": "https://api.github.com/repos/hyperledger/iroha-tui-client/merges",
    "archive_url": "https://api.github.com/repos/hyperledger/iroha-tui-client/{archive_format}{/ref}",
    "downloads_url": "https://api.github.com/repos/hyperledger/iroha-tui-client/downloads",
    "issues_url": "https://api.github.com/repos/hyperledger/iroha-tui-client/issues{/number}",
    "pulls_url": "https://api.github.com/repos/hyperledger/iroha-tui-client/pulls{/number}",
    "milestones_url": "https://api.github.com/repos/hyperledger/iroha-tui-client/milestones{/number}",
    "notifications_url": "https://api.github.com/repos/hyperledger/iroha-tui-client/notifications{?since,all,participating}",
    "labels_url": "https://api.github.com/repos/hyperledger/iroha-tui-client/labels{/name}",
    "releases_url": "https://api.github.com/repos/hyperledger/iroha-tui-client/releases{/id}",
    "deployments_url": "https://api.github.com/repos/hyperledger/iroha-tui-client/deployments",
    "created_at": "2019-10-23T15:32:28Z",
    "updated_at": "2021-04-10T09:40:57Z",
    "pushed_at": "2021-06-08T20:32:25Z",
    "git_url": "git://github.com/hyperledger/iroha-tui-client.git",
    "ssh_url": "git@github.com:hyperledger/iroha-tui-client.git",
    "clone_url": "https://github.com/hyperledger/iroha-tui-client.git",
    "svn_url": "https://github.com/hyperledger/iroha-tui-client",
    "homepage": "https://wiki.hyperledger.org/display/iroha",
    "size": 138,
    "stargazers_count": 1,
    "watchers_count": 1,
    "language": "Python",
    "has_issues": true,
    "has_projects": false,
    "has_downloads": true,
    "has_wiki": false,
    "has_pages": false,
    "forks_count": 1,
    "mirror_url": null,
    "archived": false,
    "disabled": false,
    "open_issues_count": 2,
    "license": null,
    "forks": 1,
    "open_issues": 2,
    "watchers": 1,
    "default_branch": "main",
    "permissions": {
      "pull": true,
      "triage": false,
      "push": true,
      "maintain": false,
      "admin": false
    }
  }
]
